windpytorchutils/__init__.py
windpytorchutils/filters.py
windpytorchutils/general.py
windpytorchutils/optimizers.py
windpytorchutils/samplers.py
windpytorchutils/nn/__init__.py
windpytorchutils/nn/attention_pooler.py
windPyTorchUtils-1.0.2.dist-info/LICENSE
windPyTorchUtils-1.0.2.dist-info/METADATA
windPyTorchUtils-1.0.2.dist-info/WHEEL
windPyTorchUtils-1.0.2.dist-info/top_level.txt
windPyTorchUtils-1.0.2.dist-info/RECORD
