Metadata-Version: 2.1
Name: windPyTorchUtils
Version: 1.0.2
Summary: Useful tools for PyTorch projects.
Home-page: https://github.com/windionleaf/windPyTorchUtils
Author: Martin Dočekal
License: The Unlicense
Keywords: utils,PyTorch,PyTorch utilsgeneral usage
Platform: UNKNOWN
Requires-Dist: torch (>=1.3.1)
Requires-Dist: scipy (>=1.4.1)
